topicpy/__init__.py
topicpy/TCGA_files/TCGA_files.py
topicpy/TCGA_files/__init__.py
topicpy/converter/__init__.py
topicpy/converter/converter.py
topicpy/geneontology/__init__.py
topicpy/geneontology/geneontology.py
topicpy/gtex/__init__.py
topicpy/gtex/gtex.py
topicpy/hsbmpy/__init__.py
topicpy/hsbmpy/hsbmpy.py
topicpy/hypergeom/__init__.py
topicpy/hypergeom/hypergeom.py
topicpy/lda/__init__.py
topicpy/lda/lda.py
topicpy/tableanalyser/__init__.py
topicpy/tableanalyser/tableanalyser.py
topicpy/tacos_plot/__init__.py
topicpy/tacos_plot/tacos_plot.py
topicpy-0.3.1.dist-info/LICENSE
topicpy-0.3.1.dist-info/METADATA
topicpy-0.3.1.dist-info/WHEEL
topicpy-0.3.1.dist-info/top_level.txt
topicpy-0.3.1.dist-info/RECORD
