Metadata-Version: 2.1
Name: topicpy
Version: 0.3.1
Summary: Package to extract information from topic models.
Home-page: https://github.com/fvalle1/topicpy
Author: Filippo Valle
Author-email: filippo.valle@unito.it
Classifier: Programming Language :: Python :: 3
Classifier: License :: OSI Approved :: MIT License
Classifier: Operating System :: OS Independent
Requires-Python: >=3.6
License-File: LICENSE
Requires-Dist: tensorflow
Requires-Dist: gseapy
Requires-Dist: seaborn
Requires-Dist: scikit-learn
Requires-Dist: tensorflow-probability
Requires-Dist: numpy
Requires-Dist: matplotlib
Requires-Dist: pandas
